[
    {
        "id": "Serv-001",
        "title": "Art of Equipment Zone",
        "description": "Each Powerhouse facility offers high quality cardio & strength equipment.",
        "image": "https://images.pexels.com/photos/7339473/pexels-photo-7339473.jpeg?auto=compress&cs=tinysrgb&dpr=1&w=500"
    },
    {
        "id": "Serv-002",
        "title": "Group Classes",
        "description": "We offer classes for yoga, spin, Zumba, Circuit Training, MX4 and more.",
        "image": "https://images.pexels.com/photos/3984342/pexels-photo-3984342.jpeg?auto=compress&cs=tinysrgb&dpr=2&h=650&w=940"
    },
    {
        "id": "Serv-003",
        "title": "Personal Trainers",
        "description": "Maximize your workout with the help of our personal trainers.",
        "image": "https://images.pexels.com/photos/3763874/pexels-photo-3763874.jpeg?auto=compress&cs=tinysrgb&dpr=2&h=650&w=940"
    },
    {
        "id": "Serv-004",
        "title": "Spa Services",
        "description": "Relax after an intense workout with any one of our spa services.",
        "image": "https://images.pexels.com/photos/4197801/pexels-photo-4197801.jpeg?auto=compress&cs=tinysrgb&dpr=2&h=650&w=940"
    },
    {
        "id": "Serv-005",
        "title": "Childcare",
        "description": "Enjoy your workout knowing your children are safe & nearby.",
        "image": "https://images.pexels.com/photos/3036405/pexels-photo-3036405.jpeg?auto=compress&cs=tinysrgb&dpr=2&h=650&w=940"
    },
    {
        "id": "Serv-006",
        "title": "Aquatic Pool",
        "description": "Get your cardio on in another way, by swimming laps in the pool.",
        "image": "https://images.pexels.com/photos/5563472/pexels-photo-5563472.jpeg?auto=compress&cs=tinysrgb&dpr=2&h=650&w=940"
    },
    {
        "id": "Serv-007",
        "title": "Courts",
        "description": "Workout with your friends by hitting the racquetball & basketball courts.",
        "image": "https://images.pexels.com/photos/2475878/pexels-photo-2475878.jpeg?auto=compress&cs=tinysrgb&dpr=2&h=650&w=940"
    },
    {
        "id": "Serv-008",
        "title": "Private Locker Rooms",
        "description": "Our locker rooms are equipped to help you be on your way after a workout.",
        "image": "https://images.pexels.com/photos/4162591/pexels-photo-4162591.jpeg?auto=compress&cs=tinysrgb&dpr=2&h=650&w=940"
    },
    {
        "id": "Serv-009",
        "title": "24/7 Access",
        "description": "https://images.pexels.com/photos/5474298/pexels-photo-5474298.jpeg?auto=compress&cs=tinysrgb&dpr=2&h=650&w=940"
    }
]